Workbook
Name Dept: RefData!$D$1:$D$20
Name Impact_Sustain: RefData!#REF!
Name Owner_IT: RefData!$E$1:$E$20
Name Plateforme: RefData!$C$1:$C$10
Name Priorité: RefData!$F$1:$F$37
Name TabStatus: TStatus[Status]
Name Type_Projet: RefData!$B$1:$B$5
Name Unité: RefData!$A$1:$A$10

Sheet RefData
A1: Unité | B1: Type de Projet | C1: Plateforme | D1: Dept | E1: Owner IT | F1: Prio | G1: Type Projet | H1: Status | I1: %
A2: CTN | B2: In house | C2: CRP | D2: CAL | E2: Jeanne | F2: 0 | G2: In house | H2: Waiting RFC | I2: 0
A3: SGL | B3: Out sourced | C3: GPAO | D3: IT | E3: Narindra | F3: 1 | G3: In house | H3: RFC approved | I3: 20
A4: CRE | C4: WEB | D4: IND | E4: Angelo | F4: 2 | G4: In house | H4: DEV started | I4: 30
A5: CTN/SGL | C5: SEAM | D5: MPF | E5: Fetra | F5: 3 | G5: In house | H5: Testing | I5: 80
A6: CTN/SGL/CRE | C6: FR-EVOLVE | D6: PRO | E6: Dani | F6: 4 | G6: In house | H6: Debugging | I6: 90
C7: ORACLE | D7: LOG | E7: Jackson | F7: 5 | G7: In house | H7: Go live | I7: 100
C8: PBI | D8: SUS | G8: Out sourced | H8: Prospection | I8: 0
G9: Out sourced | H9: Achat | I9: 30
G10: Out sourced | H10: Installation | I10: 50
G11: Out sourced | H11: Configuration | I11: 60
G12: Out sourced | H12: Data upload | I12: 70
G13: Out sourced | H13: Sécurisation | I13: 80
G14: Out sourced | H14: Formation | I14: 90
G15: Out sourced | H15: Go live | I15: 95
G16: Out sourced | H16: Après vente | I16: 100
G17: In house | H17: Cancelled | I17: 0

Sheet TDC
A1: Unité | B1: CTN
A2: prio | B2: (Tous)
A3: Deadline | B3: (Tous)
A4: % | B4: (Plusieurs éléments)
A6: Étiquettes de lignes | B6: Somme de Ticket #
A7: CAL | B7: 19
A8: IND | B8: 29
A9: IT | B9: 4
A10: MPF | B10: 2
A11: QUA | B11: 1
A12: SUST | B12: 3
A13: CTE | B13: 1
A14: AMG
A15: PO Achat
A16: Total général | B16: 59

Sheet Projets
A1: Unité | B1: Ticket # | C1: # | D1: Projet | E1: Dept | F1: Type de Projet | G1: Plateform | H1: Owner IT | I1: Power user | J1: prio | K1: Dev Volume | L1: Deadline | M1: Status_M1 | N1: Status | O1: Start Date | P1: End Date | Q1: % | R1: Avancement | S1: Commentaire
A2: CTN | B2: 1 | C2: CF006 | D2: Sofab - TT | E2: PRO | F2: In house | G2: GPAO | H2: Fetra | I2: Rehad | J2: TBC | L2: TBC | M2: Waiting RFC | N2: Go live | O2: 45684 | P2: 45954 | Q2: =VLOOKUP(N2,RefData!$H$2:$I$15,2,)/100 -> 1
A3: CTN | B3: 1 | C3: CF023 | D3: Digitalisation de la visite (priorité visite finie) | E3: IND | F3: In house | G3: WEB | H3: Angelo | I3: Tsiky | J3: 3 | L3: S/BY | M3: Formation | N3: Formation | Q3: =VLOOKUP(N3,RefData!$H$2:$I$15,2,)/100 -> 0.9 | R3: dev et test OK finalisation regle de gestion en cours et ergonomie lancer AO et décider oui/non si on va de l'avant | S3: Attente des règles de gestion de la part de l'équipe qualité pour les modifications Application en cours d'utilisation *Toujours en attentes de l'équipe qualité pour l'amelioration *Creation build pour test de la version améliorer *Bloquer au niveau de Tsiky, il n'a pas encore donnée les règles de gestion de sa part *lancement v2 après test iT S/BY PO PW
A4: CTN | B4: 1 | C4: CF055 | D4: Implémentation Orgatex a la teinturefil | E4: IND | F4: Out sourced | H4: Greg | I4: Pascal | J4: 1 | L4: S/BY | M4: DEV started | N4: DEV started | Q4: =VLOOKUP(N4,RefData!$H$2:$I$15,2,)/100 -> 0.3 | R4: sur ex-machine CFL : ok sur machine cotona : attente livraison matériel + venue Technicien S/BY PO Greg
A5: CTN | B5: 1 | C5: CF060 | D5: Digitalisation étude de faisabilité (commentaire live) | E5: PRO | F5: In house | G5: GPAO | H5: Jeanne | I5: Rehad | J5: TBC | K5: Medium | L5: TBC | M5: Waiting RFC | N5: Waiting RFC | Q5: =VLOOKUP(N5,RefData!$H$2:$I$15,2,)/100 -> 0 | R5: Attente mise à jour RFC (Thierry) (inclure Shakil pour lancer projet), faire un email à RH pour aller au bout du projet avec un ticket RFC ( ajout champ commentaire faisabilité + envoi email auto à l'emetteur de FSR)
A6: CTN | C6: CF079 | D6: Envoi colisage et facture automatiquement (paperless) signature electronique | E6: CAL | F6: In house | G6: GPAO | H6: Fetra | I6: Philibert | J6: 0 | L6: TBC | M6: Testing | N6: Go live | O6: 45376 | P6: 45412 | Q6: =VLOOKUP(N6,RefData!$H$2:$I$15,2,)/100 -> 1 | R6: Envoi packing list /facture automatique : synchronisation des données à faire instantanément. Attente feedabck Hoby cal
A7: CTN | B7: 1 | C7: CF094 | D7: Digitalisation fiche lancement commande | E7: PRO | F7: In house | G7: GPAO | H7: Jeanne | I7: Rehad | J7: TBC | K7: Medium | L7: TBC | M7: Waiting RFC | N7: RFC approved | Q7: =VLOOKUP(N7,RefData!$H$2:$I$15,2,)/100 -> 0.2 | R7: attente ajout fonctionnalité de RH, Partie CAL OK
A8: CTN | B8: 1 | C8: CF095 | D8: Modélisation prédictive | E8: IND | H8: Greg | I8: Pascal | J8: 4 | L8: S/BY | M8: Waiting RFC | N8: Waiting RFC | Q8: =VLOOKUP(N8,RefData!$H$2:$I$15,2,)/100 -> 0 | R8: stand by
A9: CTN | B9: 1 | C9: CF101 | D9: Digitalisation de la gestion des camionages (rendu confectionneur Tana/Abe et grand export) | E9: LOG | F9: In house | G9: GPAO | H9: Jeanne | I9: Marc | J9: 2 | L9: S/BY | M9: DEV started | N9: DEV started | Q9: =VLOOKUP(N9,RefData!$H$2:$I$15,2,)/100 -> 0.3 | R9: - Ajout nouvelles fonctionnalités proposées par Tiana/Aurélie/Marc - Groupages des factures en anglais (waiting réunion) S/BY PO Aurélie
A10: CTN | B10: 1 | C10: CF106 | D10: Migration FSR vers MVC | E10: IT | F10: In house | G10: WEB | H10: Fetra | I10: Jeanne | K10: High | L10: TBC | M10: DEV started | N10: Go live | O10: 45359 | P10: 45762 | Q10: =VLOOKUP(N10,RefData!$H$2:$I$15,2,)/100 -> 1 | R10: - Flow (100%) - Create(100%) - Update (100%) - Mail administration (100%) - Reporting (100%)
A11: CTN | C11: CF107 | D11: Migration Sofab MVC + Std de laize | E11: IT | F11: In house | G11: WEB | H11: Fetra | I11: Jeanne | K11: High | L11: TBC | M11: DEV started | N11: Go live | O11: 45359 | P11: 45762 | Q11: 1
A12: CTN | B12: 1 | C12: CF123 | D12: New GPAO | E12: IND | H12: Greg | I12: Pascal + team | J12: 3 | L12: S/BY | M12: Waiting RFC | N12: Waiting RFC | Q12: =VLOOKUP(N12,RefData!$H$2:$I$15,2,)/100 -> 0 | R12: Pascal : Donner synoptique GPAO (visio) Greg : Organisation appel d'offre ( en cours) Datatex : premiere session demo faite. Evalution budget reçue. Solin : a organiser troisieme editeur : ?
A13: CTN | B13: 1 | C13: CF126 | D13: Digitalisation tableau planning tissage dans PBI | E13: IND | H13: Greg | I13: Salohy | J13: 5 | L13: S/BY | M13: Waiting RFC | N13: Waiting RFC | Q13: =VLOOKUP(N13,RefData!$H$2:$I$15,2,)/100 -> 0 | R13: voir pbi cfl existant S/BY PO Shakil
A14: CTN | B14: 1 | C14: CF127a | D14: Traceability: LC/MO bulk sur GPAO | E14: IND | F14: In house | G14: GPAO | H14: Jeanne | I14: Shakil | J14: 0 | L14: TBC | M14: Go live | N14: Go live | O14: 45412 | P14: 45442 | Q14: =VLOOKUP(N14,RefData!$H$2:$I$15,2,)/100 -> 1 | R14: LC/MO par lot fournisseur: . Allocation fils par lot fournisseur (100%) . Mise à jour des stocks fils existant par rapport au lot fournisseur (100%) . Mise à jour des écrans LC/MO par lot fournisseur (100%( . Destockage fil par lot fournisseur (100%)
A15: CTN | B15: 1 | C15: CF127b | D15: Traceability - Supplier platform | E15: SUST | F15: In house | G15: GPAO | H15: Fetra | I15: LP | J15: 0 | L15: TBC | M15: Testing | N15: Go live | O15: 45369 | P15: 45427 | Q15: =VLOOKUP(N15,RefData!$H$2:$I$15,2,)/100 -> 1 | R15: - Supplier Profile (100%) - OCS|GOTS expiration control daily + send mail (100%) - PO's master=> details (100%) - Add login after test (100%)
A16: CTN | B16: 1 | C16: CF127c | D16: Traceability: TC/BCP pour CF et SGL | E16: SUST | F16: In house | G16: WEB | H16: Fetra/Jeanne | I16: LP | J16: 0 | L16: 45397 | M16: DEV started | N16: Go live | O16: 45327 | P16: 45427 | Q16: =VLOOKUP(N16,RefData!$H$2:$I$15,2,)/100 -> 1 | R16: 1- COTONA FABRICS: masse balance BCI (100%) TC organique (100%) . Liaison CRP => GPAO avec verrou et affichage automatique des données de SGL (100%) . Affichage BO SGL dans colisage, facturation, Livraison (100%) . Affichage des données Supplier (100%) . Download infos & Docs pdf . Download data Suppliers (100%) . TC result (100%) . Filtre par: All/waiting BCI/waiting OCS GOTS/waiting TC receipt (100%) . Enregistrement PO CLient CF dans le serveur avec verrou cal (100%) . Fiche des resultats test LABO en report & pdf dans le serveur avec verrou au Labo (100%) . Download auto des proofs of payments dans le plateforme (100%) . Download auto de la fiche à minima dans le plateforme (100%) 2- SOCOTA GARMENTS: BCI (100%) TC (100%) . Download infos & Docs pdf (100%)
A17: CTN | B17: 1 | C17: CF127d | D17: Traceability MCPAT sur GPAO | E17: IND | F17: In house | G17: GPAO | H17: Jeanne | I17: Shakil | J17: 2 | L17: TBC | M17: DEV started | N17: Go live | O17: 45330 | P17: 45473 | Q17: =VLOOKUP(N17,RefData!$H$2:$I$15,2,)/100 -> 1 | R17: . Données ID CARD vers GPAO (100%) . Mise à jour des MCPAT actif/non actif (100%) . Verrou validation bon uniquement pour les MCPAT actifs (100%) . Substitition MCPAT (100%) . Verrou création bon de droguerie uniquement pour les MCPAT actifs (100%) . Création recette dans GPAO pour les MCPAT actifs uniquement (100%) . Verrou saisie de production sans bon de droguerie validé (100%) Attente feedback users (Roger) - MCPAT: .Yarn dyeing 100% .Weaving 100% .At. Blanc 100% .Teinture 100% .Impression 100% .Digital Print 100% .Finishing 100%
A18: CTN | B18: 1 | C18: CF127e | D18: Traceability PO CF dans GPAO | E18: IND | F18: In house | G18: WEB | H18: Fetra/Jeanne | I18: Shakil LP | J18: 2 | L18: S/BY | M18: DEV started | N18: Testing | Q18: =VLOOKUP(N18,RefData!$H$2:$I$15,2,)/100 -> 0.8 | R18: Voir les besoins de chaque département (NEW DESIGN v1.1) - Synchronisation données GPAO vers SALES (100%) - MCPAT - Yarn - Yarn dyeing - Weaving - Finishing - Sales * Envoi facture/PL mutliples (Gouper Facture, Colisage, BT => 1 pdf par facture) (100%) * Corps mail à rajouter : client, retailer, article, style (100%) * Objet mail à rajouter : retailer, article (100%) - Store * Design (100%) * Grouper par PO (100%)
A19: CTN | B19: 1 | C19: CF133 | D19: Migration PLC vers MVC | E19: IT | F19: In house | G19: WEB | H19: Fetra | I19: Jeanne | K19: High | L19: TBC | M19: Testing | N19: Go live | O19: 45810 | P19: 45838 | Q19: =VLOOKUP(N19,RefData!$H$2:$I$15,2,)/100 -> 1 | R19: Fusion du projet vers le portail MVC (100%) | S19: *une grande difference au niveau reporting entre vs2015 et vs 2022 *Amelioration des recherches et filtres pour eviter la lenteur au niveau cahrgement des pages *Solution trouver pour l'adaptation entre les 2 versions *Correction et mis au point PLC avant mis en production *Correction et ajustement vis à vis de plc actuel *Verification et test avant mis en production
A20: CTN | B20: 1 | C20: CF134 | D20: Mail automatique « Waiting FNL » envoyé journalièrement | E20: CAL | F20: In house | G20: GPAO | H20: Jeanne | I20: DB | L20: 45604 | N20: Go live | O20: 45600 | P20: 45602 | Q20: =VLOOKUP(N20,RefData!$H$2:$I$15,2,)/100 -> 1
A21: CTN | B21: 1 | C21: CF135 | D21: Les saisies des raisons seront obligatoires pour les deux cas pour permettre à des analyses ultérieures. Ecran de saisie des causes de retard FNL | E21: CAL | F21: In house | G21: GPAO | H21: Jeanne | I21: DB | L21: 45604 | N21: Go live | O21: 45600 | P21: 45602 | Q21: =VLOOKUP(N21,RefData!$H$2:$I$15,2,)/100 -> 1
A22: CTN | B22: 1 | C22: CF136 | D22: Ecran de saisie / modification des adresses mails clients | E22: CAL | F22: In house | G22: GPAO | H22: Jeanne | I22: DB | L22: 45604 | N22: Go live | O22: 45600 | P22: 45602 | Q22: =VLOOKUP(N22,RefData!$H$2:$I$15,2,)/100 -> 1 | R22: Nous allons créer une base des données des contacts emails de nos clients par contremarque et département. Lesquels seront pris par le système lors de l’envoi de l’alerte aux clients.
A23: CTN | B23: 1 | C23: CF136 | D23: Digitalisation tableau planning - Mise à Dispo Data | E23: IND | F23: In house | G23: GPAO | H23: Jeanne | I23: Shakil | J23: 1 | L23: S/BY | M23: DEV started | N23: DEV started | O23: 45180 | Q23: =VLOOKUP(N23,RefData!$H$2:$I$15,2,)/100 -> 0.3 | R23: - Affichage automatique des LCs par rapport à la date ordo en fonction de la longueur, vitesse et rendement par metier - Drop and drag des bandelettes - Alerte si LC est en retard - Indication du status de chaque LC (planifié, sized, dyed, weaving) S/BY PO Shakil
A24: CTN | B24: 1 | C24: CF137 | D24: Commande avec mise (CT, SU, SO) | E24: IND | F24: In house | G24: GPAO | H24: Jeanne | I24: VA | J24: 0 | N24: Go live | O24: 45625 | P24: 45632 | Q24: =VLOOKUP(N24,RefData!$H$2:$I$15,2,)/100 -> 1 | R24: • Les commandes avec mise seront soldées automatiquement au moment du solde de la mise. • Une alerte sera envoyée au créateur du FSR lorsque la mise est soldée. • Si le ou les A4 ne sont pas reçus au moment du solde de la mise, le commercial coche la case « A4 pas encore reçu ». A leur réception, les commerciaux saisissent la date de réception dans la GPAO. Ces dates seront utilisées pour les analyses futures. • Un mail automatique journalier sera envoyé aux commerciaux et à l’équipe Service Produit pour les attentes A4.
A25: CTN | B25: 1 | C25: CF138 | D25: Commande sans mise (HL, LD, RL, RC, BL | E25: IND | F25: In house | G25: GPAO | H25: Jeanne | I25: VA | J25: 0 | N25: Go live | O25: 45625 | P25: 45632 | Q25: =VLOOKUP(N25,RefData!$H$2:$I$15,2,)/100 -> 1 | R25: • Le Service Produit indique, dans la GPAO, la date de la disponibilité des échantillons avec une alerte mail automatique au commercial. • Cela bascule automatiquement les informations relatives à cette commande d’échantillonnage dans l’écran prévu pour les commerciaux. • Quand tous les paramètres à l’échantillon/développement sont reçus par les commerciaux, ils doivent solder immédiatement la commande échantillonnage en saisissant le mot « COMPLETE » au champ réservé et intitulé « Status ». La date solde générée par le système correspond à la date de réception de l’échantillon/développement. • Sinon le commercial retourne les échantillons/développements au Service Produit et mettre « RETURN » dans la champ « Status » en choisissant la cause du retour (menu déroulant : spectro not received, file not complete, …). • Un mail automatique journalier sera envoyé aux commerciaux et à l’équipe Service Produit pour alerter les commandes attentes solde avec le nombre de jour d’attente.
A26: CTN | B26: 1 | C26: CF139 | D26: La traçabilité (date et user) a été ajouté dans la GPAO pour les nouveaux départements | E26: CAL | F26: In house | G26: GPAO | H26: Jeanne | I26: VA | J26: 0 | N26: Go live | O26: 45622 | P26: 45632 | Q26: =VLOOKUP(N26,RefData!$H$2:$I$15,2,)/100 -> 1
A27: CTN | B27: 1 | C27: CF140 | D27: Upload FSR en masse depuis fichier Excel dans l'appli | E27: Sales | H27: Fetra | I27: Tiana | J27: 1 | L27: Cancel | M27: Waiting RFC | N27: Waiting RFC | Q27: =VLOOKUP(N27,RefData!$H$2:$I$15,2,)/100 -> 0 | R27: - Création matrice d'import des FSR - Rajout fonctionnalité dans FSR pour Tanà seulement - Application des règles avant upload dans la BDD - Formation utilisateur (voir pour creation a partir de template) S/BY PO Greg
A28: CTN | B28: 1 | C28: CF140 | D28: Colisage / facturation automatique | E28: CAL | F28: In house | G28: GPAO | H28: Jeanne | I28: Phil | J28: 0 | N28: Go live | O28: 45642 | P28: 45667 | Q28: =VLOOKUP(N28,RefData!$H$2:$I$15,2,)/100 -> 1
A29: CTN | B29: 1 | C29: CF141 | D29: Integration fichier commande AQL dans GPAO | E29: CAL | F29: In house | G29: GPAO | H29: Jackson | I29: AQL/Dilshad | J29: 0 | L29: 45473 | M29: Waiting RFC | N29: Go live | P29: 45580 | Q29: =VLOOKUP(N29,RefData!$H$2:$I$15,2,)/100 -> 1 | R29: - Definition workflow (Ashwen) - OK - Defintion du dossier paratgé (sharepoint) - OK - Envoi Fichier JSON pour test (Ashwen) - OK - Generation auto JSON dans Sharepoint(Krishna) - OK - JSON Parsing code (Fetra)- OK - Jackson ask to add Retailer, batch number in JSON file (Krishna) - OK
A30: CTN | B30: 1 | C30: CF141 | D30: Remise sur choix AB, AR, AL de BRm Choix B = 50% automatiquement Choix A pas de remise | E30: IND | F30: In house | G30: GPAO | H30: Jeanne | I30: BRm | J30: 0 | N30: Go live | O30: 45634 | P30: 45656 | Q30: =VLOOKUP(N30,RefData!$H$2:$I$15,2,)/100 -> 1
A31: CTN | B31: 1 | C31: CF141bis | D31: Link AIL -> GPAO (new project) | E31: CAL | F31: In house | G31: GPAO | H31: Jeanne | I31: Dilshad | J31: 0 | L31: 45565 | N31: Go live | O31: 45448 | P31: 45473 | Q31: =VLOOKUP(N31,RefData!$H$2:$I$15,2,)/100 -> 1 | R31: - Ajout nouvel champ clé soit mise (bulk) ou PO GPAO (CT) dans WFX (100%) - Update batch JSON (100%) - Récuperation automatique des données GPAO à partir de ce champ clé (100%) - Dev Création automatique de la commande GPAO AIL (100%)
A32: CTN | B32: 1 | C32: CF142 | D32: Envoi donnés Gpao vers AQL | E32: CAL | F32: In house | G32: GPAO | H32: Jackson | I32: AQL/Dilshad | J32: 0 | K32: Low | L32: TBC | M32: Waiting RFC | N32: Go live | P32: 46022 | Q32: =VLOOKUP(N32,RefData!$H$2:$I$15,2,)/100 -> 1 | R32: Attente Feedback Ashwen sur relance du 31/10/24 Ashwen à dit que l'interface est actuellement géré par IA sur la base des Fichier packing list XLS et PDF de CTN 31/08/2025
A33: CTN | B33: 1 | C33: CF142 | D33: Création automatique des notes de crédit par rapport à la remise définie par la Qualité | E33: CAL | F33: In house | G33: GPAO | H33: Jeanne | I33: Phil | J33: 1 | N33: Go live | O33: 45634 | P33: 45664 | Q33: =VLOOKUP(N33,RefData!$H$2:$I$15,2,)/100 -> 1
A34: CTN | B34: 1 | C34: CF143 | D34: Digitalisation de la fiche à minima ==> FSS: Fabric Specification Sheet | E34: QUA | F34: In house | G34: GPAO | H34: Jeanne | I34: VA | J34: 0 | K34: Medium | L34: 45657 | M34: Waiting RFC | N34: Go live | O34: 45622 | P34: 45820 | Q34: =VLOOKUP(N34,RefData!$H$2:$I$15,2,)/100 -> 1 | R34: - Automatisation résultat labo par rapport aux requirements (5%) - Ajouter dans le plateforme FSR la mention obligatoire "Besoin FSS O/N ?" + alerte vers le Labo - Un écran GPAO pour afficher la liste des waiting FSS Et un cochage quand le FSS sera dispo + alerte vers le créateur du FSR - Afficher les blacklists dans la plateforme + export to EXCEL - Mail automatique dès qu'un article a été basculé en blacklist - Faire les FSS et audit SDL pour les 30 articles en best sellers - Digitalisation de la génération FSS (provisoire & définitif) en pdf avec sauvegarde automatique dans le serveur - Fichier excel avec les règles pour Checkers / TBI / Everlane - Liste des « type de garments » – ajuster la liste avec mapping avant après - Ajout des tests inexistants dans GPAO (100%) - Report FSS (provisional & definitive) 100% - Regenerate top 30 best sellers FSS - Data CF commitments => Revalider fichier Excel requirement + upload - Format standard FDS - Le resultat du test (pass/fail) est calculé par le système et non modifiable => Revoir la formule PASS/FAIL dans test result
A35: CTN | B35: 1 | C35: CF143 | D35: Digitalisation planning | E35: IND | F35: In house | G35: GPAO | H35: Jeanne | I35: LP | J35: 0 | K35: Medium | L35: 45747 | N35: Go live | O35: 45634 | P35: 45877 | Q35: =VLOOKUP(N35,RefData!$H$2:$I$15,2,)/100 -> 1 | R35: - Ecrans (02) de lancement - Ecran de planification atelier
A36: CTN | B36: 1 | C36: CF144 | D36: WIP | E36: IND | F36: In house | G36: WEB | H36: Jeanne | I36: LP | J36: 0 | K36: Medium | L36: 45747 | N36: Go live | O36: 45634 | P36: 45887 | Q36: =VLOOKUP(N36,RefData!$H$2:$I$15,2,)/100 -> 1 | R36: - Circuit par mise - Liste des mises par machine - WIP planning
A37: CTN | B37: 1 | C37: CF155 | D37: Digitalisation tableau planning - Front End | E37: PLN | F37: In house | G37: WEB | H37: Angelo | L37: S/BY | M37: Waiting RFC | N37: Waiting RFC | O37: 45208 | Q37: =VLOOKUP(N37,RefData!$H$2:$I$15,2,)/100 -> 0 | R37: Attente filtre avant de test en prod S/BY PO Shakil | S37: reprendre l'application aaprès remarque de Shakil, correction à faire
A38: CTN | B38: 1 | C38: CF157 | D38: Affectation stocks aux commandes | E38: CAL | F38: In house | G38: GPAO | H38: Jeanne | I38: Phil | J38: 0 | L38: TBC | M38: RFC approved | N38: Go live | P38: 45473 | Q38: =VLOOKUP(N38,RefData!$H$2:$I$15,2,)/100 -> 1 | R38: Message à activer si tissu dispo en stock (choix A / AB / AR). La réservaton du stock qu'aura fait le merch déclenchera la déduction du métrage en stock du métrage commandé
A39: CTN | B39: 1 | C39: CF162 | D39: Traçabilité demande de validation validation.socota.com ver 1 | E39: IND | F39: In house | G39: WEB | H39: Angelo | I39: Lovin | M39: Go live | N39: Go live | O39: 45247 | P39: 45369 | Q39: =VLOOKUP(N39,RefData!$H$2:$I$15,2,)/100 -> 1
A40: CTN | B40: 1 | C40: CF167 | D40: Verrouillage lot de fils au Planning | E40: IND | F40: In house | G40: GPAO | H40: Jeanne | I40: Shakil | M40: Go live | N40: Go live | P40: 45300 | Q40: =VLOOKUP(N40,RefData!$H$2:$I$15,2,)/100 -> 1
A41: CTN | B41: 1 | C41: CF168 | D41: Solde sampling par le commercial | E41: CAL | F41: In house | G41: GPAO | H41: Jeanne | I41: Dilshad | M41: Go live | N41: Go live | P41: 45352 | Q41: =VLOOKUP(N41,RefData!$H$2:$I$15,2,)/100 -> 1
A42: CTN | B42: 1 | C42: CF169 | D42: Nouveau choix AR à intégrer dans tous les écrans et extraction GPAO | E42: IND | F42: In house | G42: GPAO | H42: Jeanne | I42: Ony | M42: Go live | N42: Go live | P42: 45324 | Q42: =VLOOKUP(N42,RefData!$H$2:$I$15,2,)/100 -> 1
A43: CTN | B43: 1 | C43: CF170 | D43: Manufacturing Order (MO) | E43: IND | F43: In house | G43: GPAO | H43: Jeanne | I43: Shakil | M43: Go live | N43: Go live | P43: 45338 | Q43: =VLOOKUP(N43,RefData!$H$2:$I$15,2,)/100 -> 1
A44: CTN | B44: 1 | C44: CF171 | D44: Digitalisation stock IT | E44: IT | F44: In house | G44: WEB | H44: Narindra | I44: Dani | L44: TBC | M44: Testing | N44: Go live | O44: 45306 | P44: 45658 | Q44: =VLOOKUP(N44,RefData!$H$2:$I$15,2,)/100 -> 1
A45: CTN | B45: 1 | C45: CF172 | D45: Ajustement de tous les écrans du projet MO - LC par rapport au lot fournisseur | E45: IND | F45: In house | G45: GPAO | H45: Jeanne | I45: Shakil | J45: 0 | L45: S/BY | M45: Waiting RFC | N45: Go live | O45: 45348 | P45: 45442 | Q45: =VLOOKUP(N45,RefData!$H$2:$I$15,2,)/100 -> 1
A46: CTN | B46: 1 | C46: CF172 | D46: Digitalisation ITSR | E46: IT | F46: In house | G46: WEB | H46: Narindra | I46: Dani | L46: TBC | M46: Testing | N46: Go live | O46: 45306 | P46: 45658 | Q46: =VLOOKUP(N46,RefData!$H$2:$I$15,2,)/100 -> 1
A47: CTN | B47: 1 | C47: CF173 | D47: PBI Wet stage | E47: IND | F47: In house | G47: PBI | H47: Jeanne | I47: LP | M47: Go live | N47: Go live | P47: 45366 | Q47: =VLOOKUP(N47,RefData!$H$2:$I$15,2,)/100 -> 1
A48: CTN | B48: 1 | C48: CF174 | D48: LC/MO consultation | E48: IND | F48: In house | G48: GPAO | H48: Jeanne | I48: Shakil | M48: Go live | N48: Go live | P48: 45351 | Q48: =VLOOKUP(N48,RefData!$H$2:$I$15,2,)/100 -> 1
A49: CTN | B49: 1 | C49: CF175 | D49: Batch automatique de génération fichiers pdf facture, Packing list, BT, Test labo | E49: IND | F49: In house | G49: GPAO | H49: Jeanne | I49: Jeanne | J49: 0 | N49: Go live | P49: 45473 | Q49: =VLOOKUP(N49,RefData!$H$2:$I$15,2,)/100 -> 1
A50: CTN | B50: 1 | C50: CF175 | D50: Liaison CRP-GPAO | E50: CAL | F50: In house | G50: GPAO | H50: Jeanne | I50: SL | J50: 1 | L50: TBC | M50: Waiting RFC | N50: Go live | P50: 45436 | Q50: =VLOOKUP(N50,RefData!$H$2:$I$15,2,)/100 -> 1 | R50: - Etat des lieux OK - RFC TC validée par Sanjeev - Ajout Champ de liaison CRP dans la ligne de commande GPAO - Import auto des BO_LIST de CRP dans GPAO pour restreindre la saisie (contre marque - dept - saision, Besoin Certificat)
A51: CTN | B51: 1 | C51: CF175 | D51: LC/MO sampling | E51: IND | F51: In house | G51: GPAO | H51: Jeanne | I51: Rehad | J51: TBC | L51: TBC | M51: Waiting RFC | N51: Go live | O51: 45505 | P51: 45566 | Q51: =VLOOKUP(N51,RefData!$H$2:$I$15,2,)/100 -> 1 | R51: email à RH s'il faut continuer le projet ou pas
A52: CTN | B52: 1 | C52: CF176 | D52: Transfert affection mise | E52: IND | F52: In house | G52: GPAO | H52: Jeanne | I52: Jeanne | J52: 1 | L52: 45505 | N52: Go live | P52: 45473 | Q52: 1 | R52: Amélioration apportée, pour éviter le désaffectation puis réaffectation mise
A53: CTN | B53: 1 | C53: CF176 | D53: Suivi provision/claim (WEB io GPAO) | E53: CAL | F53: In house | G53: WEB | H53: Fetra/Jeanne | I53: Philibert | J53: 1 | M53: RFC approved | N53: Go live | O53: 45750 | P53: 45818 | Q53: 1 | R53: - Facturation : unité U à mettre par défaut pour les prix 650$ ou 200$ ou 25$ - Mettre un choix si surcouts à afficher dans o/c ou non Canceled PO Dilshad RFC changé (mail de VA le 10/12/2024) - Un écran de saisie des réclamations clients (100%) - Basculement de la provision en claim (100%) - Validation du Directeur cal (100%) - Cloture provision/Claim (100%)
A54: CTN | B54: 1 | C54: CF177 | D54: Gestion leakage: verrou à la facturation | E54: CAL | F54: In house | G54: GPAO | H54: Jeanne | I54: Philibert | J54: 1 | L54: TBC | M54: DEV started | N54: Go live | P54: 45473 | Q54: =VLOOKUP(N54,RefData!$H$2:$I$15,2,)/100 -> 1 | R54: Verrou à remettre à la facturation et non pas au niveau du solde Fin de facturation Y/N à revoir
A55: CTN | B55: 1 | C55: CF178 | D55: Circuit de validation des actions (CRUD) sur Booking RESA A | E55: CAL | F55: In house | G55: WEB | H55: Jeanne | I55: Philibert | J55: TBC | K55: Medium | L55: TBC | M55: Waiting RFC | N55: Waiting RFC | Q55: =VLOOKUP(N55,RefData!$H$2:$I$15,2,)/100 -> 0 | R55: - A mettre Dilshad comme destinataire pour les annulations / passage en résa A : à faire apparaitre dans l'email si liste verte ou non. - Ecran de validation pour Dilshad sur plateforme
A56: CTN | B56: 1 | C56: CF179 | D56: Lier FSS et SDL | E56: CAL | F56: In house | G56: GPAO | H56: Jeanne | I56: VA | J56: 0 | L56: 45731 | N56: Go live | O56: 45750 | P56: 45751 | Q56: =VLOOKUP(N56,RefData!$H$2:$I$15,2,)/100 -> 1 | R56: Surligner les articles dans SDL si le FSS est validé
A57: CTN | B57: 1 | C57: CF179 | D57: Traçabilité des sorties fils physique par PO | E57: SUST | F57: In house | G57: GPAO | H57: Jeanne | I57: Fetra sust | J57: 0 | K57: Medium | L57: 45951 | N57: Go live | O57: 45943 | P57: 45947 | Q57: =VLOOKUP(N57,RefData!$H$2:$I$15,2,)/100 -> 1 | R57: Pour audit à partir du 20/10/2025
A58: CTN | B58: 1 | C58: CF180 | D58: Création automatique de la mise à la saisie de la date ordo | E58: IND | F58: In house | G58: GPAO | H58: Jeanne | I58: LP | J58: 0 | K58: Medium | L58: 45731 | N58: Go live | O58: 45810 | P58: 45875 | Q58: =VLOOKUP(N58,RefData!$H$2:$I$15,2,)/100 -> 1
A59: CTN | B59: 1 | C59: CF180 | D59: Validation TIAF version 2 | E59: IND | F59: In house | G59: WEB | H59: Fetra | I59: Lovin | J59: 2 | L59: TBC | M59: DEV started | N59: Go live | O59: 45373 | P59: 45427 | Q59: =VLOOKUP(N59,RefData!$H$2:$I$15,2,)/100 -> 1 | R59: _Tenir en compte le circuit de validation des utilisateurs _(possible ajout d'un fiche de validation scanner dans le plateform) _Modifier le format du mail et son contenu | S59: _Format mail en attente de template de Onintsalama _Voir la possibilité de digitaliser le fiche de validation en papier _mis au point des affichage _EN attente retour de test et vérrou sur GPAO _Mis au point des reglement à adopter
A60: CTN | B60: 1 | C60: CF181 | D60: Integration data biomass sur exce MPF dans DB achats + BI | E60: MPF | F60: In house | G60: ORACLE | H60: Jackson | I60: Sahondra | J60: TBC | L60: 45397 | N60: Go live | P60: 45397 | Q60: =VLOOKUP(N60,RefData!$H$2:$I$15,2,)/100 -> 1 | R60: BI (Laza) - en cours
A61: CTN | B61: 1 | C61: CF181 | D61: Fiabiliser SDL | E61: CAL | F61: In house | G61: GPAO | H61: Jeanne | I61: VA | J61: 0 | L61: 45731 | N61: Go live | O61: 45718 | P61: 45723 | Q61: =VLOOKUP(N61,RefData!$H$2:$I$15,2,)/100 -> 1 | R61: Revoir la liste des blacklist Séparer Blacklist et master record Debugging des articles non figuré dans SDL
A62: CTN | B62: 1 | C62: CF182 | D62: Suivi Reclammations aux fournisseurs | E62: MPF | F62: In house | G62: ORACLE | H62: Jackson | I62: Sahondra | J62: TBC | L62: S/BY | N62: Waiting RFC | Q62: =VLOOKUP(N62,RefData!$H$2:$I$15,2,)/100 -> 0 | R62: - RFC faite par Brm en attente validation LP
A63: CTN | B63: 1 | C63: CF182 | D63: Scanner Barcode MPF | E63: MPF | F63: In house | G63: GPAO | H63: Fetra | I63: Sahondra | J63: 2 | K63: Medium | M63: Testing | N63: Go live | O63: 45359 | P63: 46111 | Q63: =VLOOKUP(N63,RefData!$H$2:$I$15,2,)/100 -> 1 | R63: - Inventaire (Go live) - Intégration : API 100%, Mobile 100 % - Expedition : (Go live)
A64: CTN | B64: 1 | C64: CF182 | D64: Digitalisation des FDS PVH et Petit Bateau | E64: CAL | F64: In house | G64: GPAO | H64: Jeanne | I64: VA | J64: 1 | K64: Medium | L64: 45762 | N64: Go live | O64: 45718 | P64: 45814 | Q64: =VLOOKUP(N64,RefData!$H$2:$I$15,2,)/100 -> 1
A65: CTN | B65: 1 | C65: CF183 | D65: Fiche de test LABO report & pdf | E65: ind | F65: In house | G65: GPAO | H65: Jeanne | I65: Ony | J65: 1 | L65: 45427 | N65: Go live | O65: 45718 | P65: 45427 | Q65: =VLOOKUP(N65,RefData!$H$2:$I$15,2,)/100 -> 1 | R65: - Création de report (100%) - Génération automatique du fichier pdf dans le serveur (100%)
A66: CTN | B66: 1 | C66: CF184 | D66: Digitalization inventaire immo | E66: CTE | F66: In house | G66: WEB | H66: Fetra | I66: Natacha | J66: 2 | K66: Medium | L66: 45657 | N66: Go live | O66: 3-feb-25 | P66: 28-feb-25 | Q66: =VLOOKUP(N66,RefData!$H$2:$I$15,2,)/100 -> 1 | R66: • Etablir le Work Breakdown Structure : travailler sur la codification de chaque machine sur le registre immobilisation par rapport au Dimomaint. a) Déterminer les nombres de code immo b) Déterminer le temps à allouer pour réaliser le projet. c) Définir le champion d) Etablir le planning de réalisation e) Date définie pour finir le projet en entier. • Travailler avec l’IT sur la migration des codes en codes-barres et l’application qui va avec. • Coller chaque code-barres sur chaque machine.
A67: CTN | B67: 1 | C67: CF185 | D67: FDS via EXCEL formaté sur Stimulsoft | E67: IND | F67: In house | H67: Jeanne | I67: LP | J67: 0 | K67: High | L67: 45808 | N67: Go live | O67: 45791 | P67: 45870 | Q67: =VLOOKUP(N67,RefData!$H$2:$I$15,2,)/100 -> 1 | R67: ORVIS FULL BEAUTY BROOKS J.CREW PETIT BATEAU
A68: CTN | B68: 1 | C68: CF185 | D68: Solde LC obligatoire même si le métrage n'est pas complet (<86%) et avec causes saisies par le Planning | E68: IND | F68: In house | G68: GPAO | H68: Jeanne | I68: TR | J68: 1 | L68: 45758 | N68: Go live | O68: 45744 | P68: 45758 | Q68: =VLOOKUP(N68,RefData!$H$2:$I$15,2,)/100 -> 1
A69: CTN | B69: 1 | C69: CF186 | D69: Règles de gestion SDL | E69: IND | F69: In house | G69: GPAO | H69: Jeanne | I69: VA | J69: 0 | L69: 45789 | N69: Go live | O69: 45782 | P69: 45786 | Q69: =VLOOKUP(N69,RefData!$H$2:$I$15,2,)/100 -> 1
A70: CTN | B70: 1 | C70: CF186 | D70: Retour tissu au Visitage Ecru pour REVISITAGE | E70: IND | F70: In house | G70: GPAO | H70: Jeanne | I70: Sahondra/Laza | J70: 1 | K70: Medium | L70: 45808 | N70: DEV started | O70: 45782 | Q70: =VLOOKUP(N70,RefData!$H$2:$I$15,2,)/100 -> 0.3
A71: CTN | B71: 1 | C71: CF187 | D71: Dashboard claim | E71: CAL | F71: In house | H71: Jeanne | I71: LP | N71: Go live | O71: 45810 | P71: 45827 | Q71: =VLOOKUP(N71,RefData!$H$2:$I$15,2,)/100 -> 1
A72: CTN | B72: 1 | C72: CF187 | D72: Digitalisation process route avec écran de groupage des EMS approved | E72: IND | F72: In house | G72: GPAO | H72: Jeanne | I72: LP | J72: 0 | K72: High | N72: Go live | O72: 45810 | P72: 45855 | Q72: =VLOOKUP(N72,RefData!$H$2:$I$15,2,)/100 -> 1
A73: CTN | B73: 1 | C73: CF188 | D73: Gestion des pannes machine par START - STOP | E73: IND | F73: In house | G73: GPAO | H73: Jeanne | I73: LP | J73: 0 | K73: High | N73: Go live | O73: 45810 | P73: 45853 | Q73: =VLOOKUP(N73,RefData!$H$2:$I$15,2,)/100 -> 1
A74: CTN | B74: 1 | C74: CF189 | D74: Gestion des retards, OTIF par le Planning | E74: IND | F74: In house | G74: GPAO | H74: Jeanne | I74: LP | J74: 0 | K74: High | N74: Go live | O74: 45810 | P74: 45853 | Q74: =VLOOKUP(N74,RefData!$H$2:$I$15,2,)/100 -> 1
A75: CTN | B75: 1 | C75: CF190 | D75: - Identification de la scission à la visite - Donner accès à la visite pour faire la scission de mise avec une autorisation reduite | E75: IND | F75: In house | G75: GPAO | H75: Jeanne | I75: LP | J75: 0 | K75: High | N75: Go live | O75: 45810 | P75: 45855 | Q75: =VLOOKUP(N75,RefData!$H$2:$I$15,2,)/100 -> 1
A76: CTN | B76: 1 | C76: CF191 | D76: Reconciliation métrage par step de production (par défaut +/- 7%). Verrou à mettre à chaque stade de production | E76: IND | F76: In house | G76: GPAO | H76: Jeanne | I76: LP | J76: 0 | K76: High | N76: Go live | O76: 45810 | P76: 45846 | Q76: =VLOOKUP(N76,RefData!$H$2:$I$15,2,)/100 -> 1
A77: CTN | B77: 1 | C77: CF192 | D77: Gestion des finitions mécaniques par commande commerciale | E77: IND | F77: In house | G77: GPAO | H77: Jeanne | I77: LP | J77: 0 | K77: High | L77: S/BY | N77: DEV started | Q77: =VLOOKUP(N77,RefData!$H$2:$I$15,2,)/100 -> 0.3
A78: CTN | B78: 1 | C78: CF193 | D78: Création automatique de la commande GPAO à partir du booking | E78: CAL | F78: In house | G78: WEB | H78: Jeanne | I78: Phil | J78: 0 | K78: High | L78: S/BY | N78: Waiting RFC | Q78: =VLOOKUP(N78,RefData!$H$2:$I$15,2,)/100 -> 0 | R78: S/by
A79: CTN | B79: 1 | C79: CF194 | D79: Gestion des destinataires/copies du mail automatique O/C | E79: CAL | F79: In house | G79: GPAO | H79: Jeanne | I79: Aina | J79: 1 | L79: 45961 | N79: Go live | O79: 45931 | P79: 45937 | Q79: =VLOOKUP(N79,RefData!$H$2:$I$15,2,)/100 -> 1
A80: CTN | B80: 1 | C80: CF195 | D80: Création automatique des notes de crédit générée par le Claim validé par LP | E80: CAL | F80: In house | G80: WEB | H80: Jeanne | I80: Phil | J80: 2 | N80: Waiting RFC | Q80: =VLOOKUP(N80,RefData!$H$2:$I$15,2,)/100 -> 0
A81: CTN | B81: 1 | C81: CF196-1 | D81: Amelioration WIP Production CF | E81: IND | F81: In house | G81: WEB | H81: Fetra/Jeanne | I81: LP | J81: 0 | K81: Medium | M81: Debugging | N81: Go live | O81: 45986 | P81: 46100 | Q81: =VLOOKUP(N81,RefData!$H$2:$I$15,2,)/100 -> 1 | R81: Demande recue le 25/11/2025 Attente Regles de Gestion
A82: CTN | B82: 1 | C82: CF197 | D82: WIP planning dans le plateforme | E82: IND | F82: In house | G82: WEB | H82: Fetra/Jeanne | I82: TR | J82: 1 | N82: Go live | O82: 45950 | P82: 45964 | Q82: =VLOOKUP(N82,RefData!$H$2:$I$15,2,)/100 -> 1 | R82: Eviter le batch dans le serveur (création view)
A83: CTN | B83: 1 | C83: CF198 | D83: Filtre et rang des machines par atelier | E83: IND | F83: In house | G83: WEB | H83: Fetra/Jeanne | I83: TR | J83: 1 | N83: Go live | O83: 45950 | P83: 45964 | Q83: =VLOOKUP(N83,RefData!$H$2:$I$15,2,)/100 -> 1
A84: CTN | B84: 1 | C84: CF199 | D84: Cause de la conformité des tissus | E84: IND | F84: In house | G84: GPAO | H84: Jeanne | I84: TR | J84: 2 | K84: Medium | N84: Go live | O84: 45944 | P84: 45950 | Q84: =VLOOKUP(N84,RefData!$H$2:$I$15,2,)/100 -> 1
A85: CTN | B85: 1 | C85: CF200 | D85: Identifier la scission à la visite en attente gamme | E85: IND | F85: In house | G85: GPAO | H85: Jeanne | I85: TR | J85: 2 | N85: Go live | O85: 45950 | P85: 45961 | Q85: =VLOOKUP(N85,RefData!$H$2:$I$15,2,)/100 -> 1
A86: CTN | B86: 1 | C86: CF201 | D86: Scinder le métrage à la visite en trois colonnes: - métrage initial avant scission - métrage scindé - métrage réel (final) | E86: IND | F86: In house | G86: WEB | H86: Jeanne | I86: TR | J86: 1 | L86: 45961 | N86: Go live | O86: 45929 | P86: 45940 | Q86: =VLOOKUP(N86,RefData!$H$2:$I$15,2,)/100 -> 1
A87: CTN | B87: 1 | C87: CF202 | D87: Mentionné avec des codes couleurs les wet stage (rouge) et les mises dormant (rouge flash) | E87: IND | F87: In house | G87: WEB | H87: Fetra/Jeanne | I87: TR | J87: 1 | L87: 45940 | N87: Go live | P87: 45951 | Q87: =VLOOKUP(N87,RefData!$H$2:$I$15,2,)/100 -> 1
A88: CTN | B88: 1 | C88: CF203 | D88: Traitement en temps masqué | E88: IND | F88: In house | G88: GPAO | H88: Jeanne | I88: TR | J88: 2 | N88: Waiting RFC | Q88: =VLOOKUP(N88,RefData!$H$2:$I$15,2,)/100 -> 0
A89: CTN | B89: 1 | C89: CF204 | D89: Demande automatique de remise par coupe à expédier | E89: CAL | F89: In house | G89: GPAO | H89: Jeanne | I89: Phil | J89: 1 | N89: Go live | O89: 45950 | P89: 45961 | Q89: =VLOOKUP(N89,RefData!$H$2:$I$15,2,)/100 -> 1
A90: CTN | B90: 1 | C90: CF205 | D90: Verrou création colisage/facturation automatique s'il n'y a pas de taux de bonification sur les choix AB et AR Pour les choix B et C, le taux sera automatiquement 50% | E90: CAL | F90: In house | G90: GPAO | H90: Jeanne | I90: Phil | J90: 1 | L90: 45961 | N90: Go live | O90: 45950 | P90: 45961 | Q90: =VLOOKUP(N90,RefData!$H$2:$I$15,2,)/100 -> 1
A91: CTN | B91: 1 | C91: CF206 | D91: Ecran de saisie des bonifications au niveau Quality | E91: CAL | F91: In house | G91: GPAO | H91: Jeanne | I91: Phil | J91: 1 | L91: 45961 | N91: Go live | O91: 45950 | P91: 45961 | Q91: =VLOOKUP(N91,RefData!$H$2:$I$15,2,)/100 -> 1
A92: CTN | B92: 1 | C92: CF207 | D92: Ajustement édition FSS par test/norme | E92: QUA | F92: In house | G92: GPAO | H92: Jeanne | I92: Tojo | J92: 1 | L92: 45950 | N92: Go live | O92: 45936 | P92: 45945 | Q92: =VLOOKUP(N92,RefData!$H$2:$I$15,2,)/100 -> 1
A93: CTN | B93: 1 | C93: CF208 | D93: WIP variances par Responsable | E93: IND | F93: In house | G93: WEB | H93: Fetra/Jeanne | I93: LP | J93: 0 | L93: 45991 | N93: Go live | O93: 45951 | P93: 45960 | Q93: =VLOOKUP(N93,RefData!$H$2:$I$15,2,)/100 -> 1
A94: CTN | B94: 1 | C94: CF209 | D94: Bonjour, Merci de mettre en place la solde commande automatique suite mail en attache svp, ci-dessous la règle de gestion: - Oui pour + ou – 97 % - Pas de mises en cours - Que sur les commandes réellement livrées, c'est à dire facture embarquées | E94: CAL | F94: In house | G94: WEB | H94: Jeanne | I94: Phil | J94: 1 | K94: Medium | L94: 45991 | N94: Go live | O94: 45966 | P94: 45989 | Q94: =VLOOKUP(N94,RefData!$H$2:$I$15,2,)/100 -> 1
A95: CTN | B95: 1 | C95: CF210 | D95: Anticiper les anomalies interface GPAO vers SUN System | E95: CAL | F95: In house | G95: GPAO | H95: Jeanne | I95: Fredon CTE | J95: 1 | L95: 45982 | N95: Go live | O95: 45972 | P95: 45978 | Q95: =VLOOKUP(N95,RefData!$H$2:$I$15,2,)/100 -> 1
A96: CTN | B96: 1 | C96: CF211 | D96: Discount at source: | E96: CAL | F96: In house | G96: GPAO | H96: Jeanne | I96: Phil | J96: 0 | K96: High | L96: 46022 | N96: Go live | O96: 45951 | P96: 46022 | Q96: =VLOOKUP(N96,RefData!$H$2:$I$15,2,)/100 -> 1 | R96: Sasie discount Edition facture Factures émises Facturation pièces Stat par article Stat par client Réintegration avec discount Retour avec discont Interface GPAO - SUN
A97: CTN | B97: 1 | C97: CF212 | D97: New SDL | E97: CAL | F97: In house | G97: GPAO | H97: Jeanne | I97: VA | J97: 0 | K97: High | L97: 46053 | N97: Go live | O97: 45995 | P97: 46069 | Q97: =VLOOKUP(N97,RefData!$H$2:$I$15,2,)/100 -> 1 | R97: -Identifier EMS racine (UT: conventionnel, TT: 1ère création sans extension), mère et fille dans EMS_EMPLOI_MATIERES (100%) - Nouvel écran de duplication EMS automatique (100%) - Bloquer la duplication si l'EMS n'est pas mère (100%) - Création automatique des articles finis, écru, base, ems_article_finis au moment de la création commande GPAO (10%) - Autoriser la création PO dans CRP même si l'article fini n'existe pas. A créer au moment de la création commande GPAO (100%)
A98: CTN | B98: 1 | C98: CF213 | D98: SGL PO avec mention "NEW RULE" | E98: CAL | F98: In house | G98: WEB | H98: Jeanne | I98: LP | J98: 0 | K98: High | L98: 45796 | N98: Go live | O98: 45791 | P98: 45792 | Q98: =VLOOKUP(N98,RefData!$H$2:$I$15,2,)/100 -> 1 | R98: - Fiche suiveuse - Bilan commande - Saisie date ordo - Fiche d'approbation - Création commande
A99: CTN | C99: CF215 | D99: PO Achat | E99: AMG | F99: In house | G99: WEB | H99: Fanilo | I99: Tina | J99: 0 | K99: Medium | L99: 45777 | N99: Go live | O99: 45734 | P99: 45866 | Q99: =VLOOKUP(N99,RefData!$H$2:$I$15,2,)/100 -> 1 | R99: L'ajout de l'affichage des budgets des PO sur la page des valideurs de la plateforme a déjà été réalisé. La mise en service est en attente de la disponibilité de Laza.
A100: CTN | B100: 1 | C100: CF216 | D100: Incoterm réel par facture au moment de l'éxpedition (obligatoire) | E100: CAL | F100: In house | G100: GPAO | H100: Jeanne | I100: Phil | J100: 0 | K100: Medium | L100: 46031 | N100: Go live | O100: 46028 | P100: 46031 | Q100: =VLOOKUP(N100,RefData!$H$2:$I$15,2,)/100 -> 1
...

Sheet Tkt
A1: Ticket # | B1: Close Date
A2: 24518 | B2: 45302
A3: 24530 | B3: 45296
A4: 24670 | B4: 45307
A5: 24673 | B5: 45337
A6: 24709 | B6: 45306
A7: 24822 | B7: 45322
A8: 24843 | B8: 45313
A9: 24845 | B9: 45313
A10: 24857 | B10: 45322
A11: 24864 | B11: 45315
A12: 24879 | B12: 45321
A13: 24927 | B13: 45323
... A37: 25746 | B37: 45582
A38: 25768
A39: 25771 | B39: 45400
A40: 25789
A41: 25790 | B41: 45385
A42: 25813 | B42: 45372
A43: 25840 | B43: 45387
A44: 25845 | B44: 45372
A45: 25922 | B45: 45407
A46: 25925 | B46: 45378
A47: 25928 | B47: 45377
A48: 25952 | B48: 45400
A49: 25971 | B49: 45385
A50: 25977 | B50: 45385
A51: 25980 | B51: 45385
A52: 26046 | B52: 45391
... A89: 27321 | B89: 45531
A90: 27355
A91: 27356 | B91: 45484
A92: 27384 | B92: 45485
A93: 27429 | B93: 45489
A94: 27440 | B94: 45491
A95: 27482 | B95: 45496
A96: 27483 | B96: 45503
A97: 27520 | B97: 45495
A98: 27531 | B98: 45496
A99: 27576 | B99: 45498
A100: 27607 | B100: 45505
A101: 27666 | B101: 45505
A102: 27725 | B102: 45509
... A127: 28404 | B127: 45594
A128: 28444
A129: 28459 | B129: 45566
A130: 28465 | B130: 45579
A131: 28517 | B131: 45561
A132: 28545 | B132: 45572
A133: 28579 | B133: 45567
A134: 28615 | B134: 45568
A135: 28621 | B135: 45595
A136: 28701 | B136: 45579
A137: 28731 | B137: 45610
A138: 28859 | B138: 45708
A139: 28936 | B139: 45610
A140: 28949 | B140: 45610
... A142: 29030 | B142: 45595
A143: 29047
A144: 29178 | B144: 45629
A145: 29179 | B145: 45611
A146: 29241 | B146: 45615
A147: 29302 | B147: 45614
A148: 29347 | B148: 45663
A149: 29366 | B149: 45617
A150: 29453 | B150: 45708
A151: 29465 | B151: 45635
A152: 29495 | B152: 45625
A153: 29510 | B153: 45629
A154: 29583 | B154: 45635
A155: 29677 | B155: 45638
... A183: 30909 | B183: 45723
A184: 30925
A185: 30926 | B185: 45726
A186: 30961 | B186: 45737
A187: 31085 | B187: 45734
A188: 31094
A189: 31109 | B189: 45733
A190: 31137 | B190: 45740
A191: 31172 | B191: 45741
A192: 31203 | B192: 45737
A193: 31225
A194: 31236
A195: 31253
